zhenyagreeting/__init__.py
zhenyagreeting/hello.py
zhenyagreeting-0.1.0.dist-info/METADATA
zhenyagreeting-0.1.0.dist-info/WHEEL
zhenyagreeting-0.1.0.dist-info/top_level.txt
zhenyagreeting-0.1.0.dist-info/RECORD
